[{"order_id":"CA-2018-105893","order_date":"11-11-2018","ship_date":"18-11-2018","ship_mode":"Standard Class","customer_id":"PK-19075","region":"Central","product_id":"OFF-ST-10004186","category":"Office Supplies","sales":665.9,"quantity":6,"profit":13.3,"return_order_id":"CA-2018-105893","return_reason":"bad quality","_merge":"both"},{"order_id":"CA-2018-115812","order_date":"09-06-2018","ship_date":"14-06-2018","ship_mode":"Standard Class","customer_id":"BH-11710","region":"West","product_id":"FUR-FU-10001487","category":"Furniture","sales":48.9,"quantity":7,"profit":14.2,"return_order_id":null,"return_reason":null,"_merge":"left_only"},{"order_id":"CA-2018-115812","order_date":"09-06-2018","ship_date":"14-06-2018","ship_mode":"Standard Class","customer_id":"BH-11710","region":"West","product_id":"OFF-AR-10002833","category":"Office Supplies","sales":7.3,"quantity":4,"profit":2.0,"return_order_id":null,"return_reason":null,"_merge":"left_only"},{"order_id":"CA-2018-115812","order_date":"09-06-2018","ship_date":"14-06-2018","ship_mode":"Standard Class","customer_id":"BH-11710","region":"West","product_id":"TEC-PH-10002275","category":"Technology","sales":907.2,"quantity":6,"profit":90.7,"return_order_id":null,"return_reason":null,"_merge":"left_only"},{"order_id":"CA-2018-115812","order_date":"09-06-2018","ship_date":"14-06-2018","ship_mode":"Standard Class","customer_id":"BH-11710","region":"West","product_id":"OFF-BI-10003910","category":"Office Supplies","sales":18.5,"quantity":3,"profit":5.8,"return_order_id":null,"return_reason":null,"_merge":"left_only"},{"order_id":"CA-2018-115812","order_date":"09-06-2018","ship_date":"14-06-2018","ship_mode":"Standard Class","customer_id":"BH-11710","region":"West","product_id":"OFF-AP-10002892","category":"Office Supplies","sales":114.9,"quantity":5,"profit":34.5,"return_order_id":null,"return_reason":null,"_merge":"left_only"},{"order_id":"CA-2018-115812","order_date":"09-06-2018","ship_date":"14-06-2018","ship_mode":"Standard Class","customer_id":"BH-11710","region":"West","product_id":"FUR-TA-10001539","category":"Furniture","sales":1706.2,"quantity":9,"profit":85.3,"return_order_id":null,"return_reason":null,"_merge":"left_only"},{"order_id":"CA-2018-115812","order_date":"09-06-2018","ship_date":"14-06-2018","ship_mode":"Standard Class","customer_id":"BH-11710","region":"West","product_id":"TEC-PH-10002033","category":"Technology","sales":911.4,"quantity":4,"profit":68.4,"return_order_id":null,"return_reason":null,"_merge":"left_only"},{"order_id":"CA-2018-143336","order_date":"27-08-2018","ship_date":"01-09-2018","ship_mode":"Second Class","customer_id":"ZD-21925","region":"West","product_id":"OFF-AR-10003056","category":"Office Supplies","sales":8.6,"quantity":2,"profit":2.5,"return_order_id":"CA-2018-143336","return_reason":"wrong item","_merge":"both"},{"order_id":"CA-2018-143336","order_date":"27-08-2018","ship_date":"01-09-2018","ship_mode":"Second Class","customer_id":"ZD-21925","region":"West","product_id":"TEC-PH-10001949","category":"Technology","sales":213.5,"quantity":3,"profit":16.0,"return_order_id":"CA-2018-143336","return_reason":"wrong item","_merge":"both"},{"order_id":"CA-2018-143336","order_date":"27-08-2018","ship_date":"01-09-2018","ship_mode":"Second Class","customer_id":"ZD-21925","region":"West","product_id":"OFF-BI-10002215","category":"Office Supplies","sales":22.7,"quantity":4,"profit":7.4,"return_order_id":"CA-2018-143336","return_reason":"wrong item","_merge":"both"},{"order_id":"CA-2018-146703","order_date":"20-10-2018","ship_date":"25-10-2018","ship_mode":"Second Class","customer_id":"PO-18865","region":"Central","product_id":"OFF-ST-10001713","category":"Office Supplies","sales":212.0,"quantity":4,"profit":8.5,"return_order_id":"CA-2018-146703","return_reason":"wrong item","_merge":"both"},{"order_id":"CA-2018-167164","order_date":"13-05-2018","ship_date":"15-05-2018","ship_mode":"Second Class","customer_id":"AG-10270","region":"West","product_id":"OFF-ST-10000107","category":"Office Supplies","sales":55.5,"quantity":2,"profit":10.0,"return_order_id":"CA-2018-167164","return_reason":"other","_merge":"both"},{"order_id":"CA-2019-106320","order_date":"25-09-2019","ship_date":"30-09-2019","ship_mode":"Standard Class","customer_id":"EB-13870","region":"West","product_id":"FUR-TA-10000577","category":"Furniture","sales":1044.6,"quantity":3,"profit":240.3,"return_order_id":"CA-2019-106320","return_reason":"bad quality","_merge":"both"},{"order_id":"CA-2019-115742","order_date":"18-04-2019","ship_date":"22-04-2019","ship_mode":"Standard Class","customer_id":"DP-13000","region":"Central","product_id":"OFF-BI-10004410","category":"Office Supplies","sales":38.2,"quantity":6,"profit":18.0,"return_order_id":"CA-2019-115742","return_reason":"other","_merge":"both"},{"order_id":"CA-2019-117415","order_date":"27-12-2019","ship_date":"31-12-2019","ship_mode":"Standard Class","customer_id":"SN-20710","region":"Central","product_id":"OFF-EN-10002986","category":"Office Supplies","sales":113.3,"quantity":9,"profit":35.4,"return_order_id":null,"return_reason":null,"_merge":"left_only"},{"order_id":"CA-2019-117415","order_date":"27-12-2019","ship_date":"31-12-2019","ship_mode":"Standard Class","customer_id":"SN-20710","region":"Central","product_id":"FUR-BO-10002545","category":"Furniture","sales":532.4,"quantity":3,"profit":-47.0,"return_order_id":null,"return_reason":null,"_merge":"left_only"},{"order_id":"CA-2019-117415","order_date":"27-12-2019","ship_date":"31-12-2019","ship_mode":"Standard Class","customer_id":"SN-20710","region":"Central","product_id":"FUR-CH-10004218","category":"Furniture","sales":212.1,"quantity":3,"profit":-15.1,"return_order_id":null,"return_reason":null,"_merge":"left_only"},{"order_id":"CA-2019-117415","order_date":"27-12-2019","ship_date":"31-12-2019","ship_mode":"Standard Class","customer_id":"SN-20710","region":"Central","product_id":"TEC-PH-10000486","category":"Technology","sales":371.2,"quantity":4,"profit":41.8,"return_order_id":null,"return_reason":null,"_merge":"left_only"},{"order_id":"CA-2020-101343","order_date":"17-07-2020","ship_date":"22-07-2020","ship_mode":"Standard Class","customer_id":"RA-19885","region":"West","product_id":"OFF-ST-10003479","category":"Office Supplies","sales":77.9,"quantity":2,"profit":3.9,"return_order_id":"CA-2020-101343","return_reason":"bad quality","_merge":"both"},{"order_id":"CA-2020-117590","order_date":"08-12-2020","ship_date":"10-12-2020","ship_mode":"First Class","customer_id":"GH-14485","region":"Central","product_id":"TEC-PH-10004977","category":"Technology","sales":1097.5,"quantity":7,"profit":123.5,"return_order_id":"CA-2020-117590","return_reason":"wrong item","_merge":"both"},{"order_id":"CA-2020-117590","order_date":"08-12-2020","ship_date":"10-12-2020","ship_mode":"First Class","customer_id":"GH-14485","region":"Central","product_id":"FUR-FU-10003664","category":"Furniture","sales":190.9,"quantity":5,"profit":-148.0,"return_order_id":"CA-2020-117590","return_reason":"wrong item","_merge":"both"},{"order_id":"CA-2020-118255","order_date":"11-03-2020","ship_date":"13-03-2020","ship_mode":"First Class","customer_id":"ON-18715","region":"Central","product_id":"TEC-AC-10000171","category":"Technology","sales":46.0,"quantity":2,"profit":19.8,"return_order_id":null,"return_reason":null,"_merge":"left_only"},{"order_id":"CA-2020-118255","order_date":"11-03-2020","ship_date":"13-03-2020","ship_mode":"First Class","customer_id":"ON-18715","region":"Central","product_id":"OFF-BI-10003291","category":"Office Supplies","sales":17.5,"quantity":2,"profit":8.2,"return_order_id":null,"return_reason":null,"_merge":"left_only"},{"order_id":"CA-2020-121755","order_date":"16-01-2020","ship_date":"20-01-2020","ship_mode":"Second Class","customer_id":"EH-13945","region":"West","product_id":"OFF-BI-10001634","category":"Office Supplies","sales":11.6,"quantity":2,"profit":4.2,"return_order_id":null,"return_reason":null,"_merge":"left_only"},{"order_id":"CA-2020-121755","order_date":"16-01-2020","ship_date":"20-01-2020","ship_mode":"Second Class","customer_id":"EH-13945","region":"West","product_id":"TEC-AC-10003027","category":"Technology","sales":90.6,"quantity":3,"profit":11.8,"return_order_id":null,"return_reason":null,"_merge":"left_only"},{"order_id":"CA-2020-137330","order_date":"09-12-2020","ship_date":"13-12-2020","ship_mode":"Standard Class","customer_id":"KB-16585","region":"Central","product_id":"OFF-AR-10000246","category":"Office Supplies","sales":19.5,"quantity":7,"profit":5.1,"return_order_id":null,"return_reason":null,"_merge":"left_only"},{"order_id":"CA-2020-137330","order_date":"09-12-2020","ship_date":"13-12-2020","ship_mode":"Standard Class","customer_id":"KB-16585","region":"Central","product_id":"OFF-AP-10001492","category":"Office Supplies","sales":60.3,"quantity":7,"profit":15.7,"return_order_id":null,"return_reason":null,"_merge":"left_only"},{"order_id":"CA-2020-138688","order_date":"12-06-2020","ship_date":"16-06-2020","ship_mode":"Second Class","customer_id":"DV-13045","region":"West","product_id":"OFF-LA-10000240","category":"Office Supplies","sales":14.6,"quantity":2,"profit":6.9,"return_order_id":null,"return_reason":null,"_merge":"left_only"},{"order_id":"CA-2020-152156","order_date":"08-11-2020","ship_date":"11-11-2020","ship_mode":"Second Class","customer_id":"CG-12520","region":"South","product_id":"FUR-BO-10001798","category":"Furniture","sales":262.0,"quantity":2,"profit":41.9,"return_order_id":null,"return_reason":null,"_merge":"left_only"},{"order_id":"CA-2020-152156","order_date":"08-11-2020","ship_date":"11-11-2020","ship_mode":"Second Class","customer_id":"CG-12520","region":"South","product_id":"FUR-CH-10000454","category":"Furniture","sales":731.9,"quantity":3,"profit":219.6,"return_order_id":null,"return_reason":null,"_merge":"left_only"},{"order_id":"CA-2020-161389","order_date":"05-12-2020","ship_date":"10-12-2020","ship_mode":"Standard Class","customer_id":"IM-15070","region":"West","product_id":"OFF-BI-10003656","category":"Office Supplies","sales":408.0,"quantity":3,"profit":132.6,"return_order_id":null,"return_reason":null,"_merge":"left_only"},{"order_id":"CA-2020-169194","order_date":"20-06-2020","ship_date":"25-06-2020","ship_mode":"Standard Class","customer_id":"LH-16900","region":"East","product_id":"TEC-AC-10002167","category":"Technology","sales":45.0,"quantity":3,"profit":5.0,"return_order_id":null,"return_reason":null,"_merge":"left_only"},{"order_id":"CA-2020-169194","order_date":"20-06-2020","ship_date":"25-06-2020","ship_mode":"Standard Class","customer_id":"LH-16900","region":"East","product_id":"TEC-PH-10003988","category":"Technology","sales":21.8,"quantity":2,"profit":6.1,"return_order_id":null,"return_reason":null,"_merge":"left_only"},{"order_id":"CA-2021-107727","order_date":"19-10-2021","ship_date":"23-10-2021","ship_mode":"Second Class","customer_id":"MA-17560","region":"Central","product_id":"OFF-PA-10000249","category":"Office Supplies","sales":29.5,"quantity":3,"profit":9.9,"return_order_id":null,"return_reason":null,"_merge":"left_only"},{"order_id":"CA-2021-114412","order_date":"15-04-2021","ship_date":"20-04-2021","ship_mode":"Standard Class","customer_id":"AA-10480","region":"South","product_id":"OFF-PA-10002365","category":"Office Supplies","sales":15.6,"quantity":3,"profit":5.4,"return_order_id":null,"return_reason":null,"_merge":"left_only"},{"order_id":"CA-2021-120999","order_date":"10-09-2021","ship_date":"15-09-2021","ship_mode":"Standard Class","customer_id":"LC-16930","region":"Central","product_id":"TEC-PH-10004093","category":"Technology","sales":147.2,"quantity":4,"profit":16.6,"return_order_id":null,"return_reason":null,"_merge":"left_only"},{"order_id":"CA-2021-139619","order_date":"19-09-2021","ship_date":"23-09-2021","ship_mode":"Standard Class","customer_id":"ES-14080","region":"South","product_id":"OFF-ST-10003282","category":"Office Supplies","sales":95.6,"quantity":2,"profit":9.6,"return_order_id":null,"return_reason":null,"_merge":"left_only"},{"order_id":"US-2019-108966","order_date":"11-10-2019","ship_date":"18-10-2019","ship_mode":"Standard Class","customer_id":"SO-20335","region":"South","product_id":"FUR-TA-10000577","category":"Furniture","sales":957.6,"quantity":5,"profit":-383.0,"return_order_id":null,"return_reason":null,"_merge":"left_only"},{"order_id":"US-2019-108966","order_date":"11-10-2019","ship_date":"18-10-2019","ship_mode":"Standard Class","customer_id":"SO-20335","region":"South","product_id":"OFF-ST-10000760","category":"Office Supplies","sales":22.4,"quantity":2,"profit":2.5,"return_order_id":null,"return_reason":null,"_merge":"left_only"},{"order_id":"US-2019-118983","order_date":"22-11-2019","ship_date":"26-11-2019","ship_mode":"Standard Class","customer_id":"HP-14815","region":"Central","product_id":"OFF-AP-10002311","category":"Office Supplies","sales":68.8,"quantity":5,"profit":-123.9,"return_order_id":null,"return_reason":null,"_merge":"left_only"},{"order_id":"US-2019-118983","order_date":"22-11-2019","ship_date":"26-11-2019","ship_mode":"Standard Class","customer_id":"HP-14815","region":"Central","product_id":"OFF-BI-10000756","category":"Office Supplies","sales":2.5,"quantity":3,"profit":-3.8,"return_order_id":null,"return_reason":null,"_merge":"left_only"},{"order_id":"US-2019-150630","order_date":"17-09-2019","ship_date":"21-09-2019","ship_mode":"Standard Class","customer_id":"TB-21520","region":"East","product_id":"FUR-BO-10004834","category":"Furniture","sales":3083.4,"quantity":7,"profit":-1665.1,"return_order_id":null,"return_reason":null,"_merge":"left_only"},{"order_id":"US-2019-150630","order_date":"17-09-2019","ship_date":"21-09-2019","ship_mode":"Standard Class","customer_id":"TB-21520","region":"East","product_id":"OFF-BI-10000474","category":"Office Supplies","sales":9.6,"quantity":2,"profit":-7.1,"return_order_id":null,"return_reason":null,"_merge":"left_only"},{"order_id":"US-2019-150630","order_date":"17-09-2019","ship_date":"21-09-2019","ship_mode":"Standard Class","customer_id":"TB-21520","region":"East","product_id":"FUR-FU-10004848","category":"Furniture","sales":124.2,"quantity":3,"profit":15.5,"return_order_id":null,"return_reason":null,"_merge":"left_only"},{"order_id":"US-2019-150630","order_date":"17-09-2019","ship_date":"21-09-2019","ship_mode":"Standard Class","customer_id":"TB-21520","region":"East","product_id":"OFF-EN-10001509","category":"Office Supplies","sales":3.3,"quantity":2,"profit":1.1,"return_order_id":null,"return_reason":null,"_merge":"left_only"},{"order_id":"US-2019-150630","order_date":"17-09-2019","ship_date":"21-09-2019","ship_mode":"Standard Class","customer_id":"TB-21520","region":"East","product_id":"OFF-AR-10004042","category":"Office Supplies","sales":86.3,"quantity":6,"profit":9.7,"return_order_id":null,"return_reason":null,"_merge":"left_only"},{"order_id":"US-2019-150630","order_date":"17-09-2019","ship_date":"21-09-2019","ship_mode":"Standard Class","customer_id":"TB-21520","region":"East","product_id":"OFF-BI-10001525","category":"Office Supplies","sales":6.9,"quantity":6,"profit":-5.7,"return_order_id":null,"return_reason":null,"_merge":"left_only"},{"order_id":"US-2019-150630","order_date":"17-09-2019","ship_date":"21-09-2019","ship_mode":"Standard Class","customer_id":"TB-21520","region":"East","product_id":"OFF-AR-10001683","category":"Office Supplies","sales":15.8,"quantity":2,"profit":3.5,"return_order_id":null,"return_reason":null,"_merge":"left_only"},{"order_id":"US-2021-156909","order_date":"16-07-2021","ship_date":"18-07-2021","ship_mode":"Second Class","customer_id":"SF-20065","region":"East","product_id":"FUR-CH-10002774","category":"Furniture","sales":71.4,"quantity":2,"profit":-1.0,"return_order_id":null,"return_reason":null,"_merge":"left_only"}]